[
    {
        "size": 19,
        "name": "match_number"
    },
    {
        "size": {
            "red": {
                "autoRobot1": "AutoRun",
                "foulPoints": 0,
                "totalPoints": 268,
                "vaultForceTotal": 3,
                "endgamePoints": 40,
                "autoSwitchAtZero": true,
                "autoSwitchOwnershipSec": 8,
                "autoRobot3": "AutoRun",
                "adjustPoints": 0,
                "vaultBoostPlayed": 1,
                "endgameRobot3": "Parking",
                "rp": 2,
                "vaultForcePlayed": 2,
                "endgameRobot2": "Levitate",
                "vaultLevitateTotal": 3,
                "teleopSwitchBoostSec": 10,
                "endgameRobot1": "Parking",
                "teleopScaleOwnershipSec": 11,
                "vaultPoints": 45,
                "faceTheBossRankingPoint": false,
                "vaultBoostTotal": 3,
                "autoPoints": 26,
                "teleopScaleForceSec": 10,
                "autoRunPoints": 10,
                "teleopSwitchForceSec": 0,
                "autoOwnershipPoints": 16,
                "teleopPoints": 242,
                "foulCount": 0,
                "techFoulCount": 0,
                "teleopOwnershipPoints": 157,
                "tba_gameData": "RRR",
                "autoRobot2": "None",
                "autoScaleOwnershipSec": 0,
                "teleopScaleBoostSec": 0,
                "vaultLevitatePlayed": 3,
                "teleopSwitchOwnershipSec": 136,
                "autoQuestRankingPoint": false
            },
            "blue": {
                "autoRobot1": "AutoRun",
                "foulPoints": 0,
                "totalPoints": 186,
                "vaultForceTotal": 1,
                "endgamePoints": 35,
                "autoSwitchAtZero": false,
                "autoSwitchOwnershipSec": 0,
                "autoRobot3": "None",
                "adjustPoints": 0,
                "vaultBoostPlayed": 0,
                "endgameRobot3": "None",
                "rp": 0,
                "vaultForcePlayed": 0,
                "endgameRobot2": "Parking",
                "vaultLevitateTotal": 3,
                "teleopSwitchBoostSec": 0,
                "endgameRobot1": "Levitate",
                "teleopScaleOwnershipSec": 0,
                "vaultPoints": 20,
                "faceTheBossRankingPoint": false,
                "vaultBoostTotal": 0,
                "autoPoints": 10,
                "teleopScaleForceSec": 0,
                "autoRunPoints": 10,
                "teleopSwitchForceSec": 0,
                "autoOwnershipPoints": 0,
                "teleopPoints": 176,
                "foulCount": 0,
                "techFoulCount": 0,
                "teleopOwnershipPoints": 121,
                "tba_gameData": "RRR",
                "autoRobot2": "AutoRun",
                "autoScaleOwnershipSec": 0,
                "teleopScaleBoostSec": 0,
                "vaultLevitatePlayed": 3,
                "teleopSwitchOwnershipSec": 121,
                "autoQuestRankingPoint": false
            }
        },
        "name": "score_breakdown"
    },
    {
        "size": 1520010493,
        "name": "actual_time"
    },
    {
        "size": 1520010668,
        "name": "post_result_time"
    },
    {
        "size": {
            "red": {
                "team_keys": [
                    "frc573",
                    "frc6096",
                    "frc4758"
                ],
                "surrogate_team_keys": [],
                "score": 268,
                "dq_team_keys": []
            },
            "blue": {
                "team_keys": [
                    "frc6136",
                    "frc5467",
                    "frc5197"
                ],
                "surrogate_team_keys": [],
                "score": 186,
                "dq_team_keys": []
            }
        },
        "name": "alliances"
    },
    {
        "size": "red",
        "name": "winning_alliance"
    },
    {
        "size": "2018misou_qm19",
        "name": "key"
    },
    {
        "size": "qm",
        "name": "comp_level"
    },
    {
        "size": 1520018820,
        "name": "predicted_time"
    },
    {
        "size": "2018misou",
        "name": "event_key"
    },
    {
        "size": [
            {
                "type": "youtube",
                "key": "_Awz61JlCCk"
            }
        ],
        "name": "videos"
    },
    {
        "size": 1520019720,
        "name": "time"
    },
    {
        "size": 1,
        "name": "set_number"
    }
]
