[
    {
        "size": 1519990872,
        "name": "post_result_time"
    },
    {
        "size": {
            "blue": {
                "foulCount": 0,
                "vaultBoostTotal": 1,
                "faceTheBossRankingPoint": false,
                "endgameRobot2": "Climbing",
                "teleopScaleForceSec": 10,
                "autoRobot2": "AutoRun",
                "teleopSwitchBoostSec": 10,
                "techFoulCount": 0,
                "teleopSwitchOwnershipSec": 136,
                "autoScaleOwnershipSec": 1,
                "autoRobot1": "AutoRun",
                "autoSwitchOwnershipSec": 11,
                "vaultLevitateTotal": 3,
                "vaultBoostPlayed": 1,
                "endgameRobot3": "None",
                "autoPoints": 39,
                "adjustPoints": 0,
                "teleopScaleOwnershipSec": 104,
                "totalPoints": 394,
                "vaultForcePlayed": 3,
                "endgameRobot1": "Levitate",
                "endgamePoints": 60,
                "autoRunPoints": 15,
                "vaultForceTotal": 3,
                "autoSwitchAtZero": true,
                "autoOwnershipPoints": 24,
                "foulPoints": 10,
                "rp": 3,
                "teleopOwnershipPoints": 250,
                "teleopSwitchForceSec": 10,
                "tba_gameData": "RRR",
                "teleopScaleBoostSec": 0,
                "autoRobot3": "AutoRun",
                "vaultPoints": 35,
                "vaultLevitatePlayed": 3,
                "autoQuestRankingPoint": true,
                "teleopPoints": 345
            },
            "red": {
                "foulCount": 2,
                "vaultBoostTotal": 0,
                "faceTheBossRankingPoint": false,
                "endgameRobot2": "None",
                "teleopScaleForceSec": 0,
                "autoRobot2": "None",
                "teleopSwitchBoostSec": 0,
                "techFoulCount": 0,
                "teleopSwitchOwnershipSec": 0,
                "autoScaleOwnershipSec": 1,
                "autoRobot1": "None",
                "autoSwitchOwnershipSec": 0,
                "vaultLevitateTotal": 0,
                "vaultBoostPlayed": 0,
                "endgameRobot3": "Parking",
                "autoPoints": 2,
                "adjustPoints": 0,
                "teleopScaleOwnershipSec": 0,
                "totalPoints": 7,
                "vaultForcePlayed": 0,
                "endgameRobot1": "None",
                "endgamePoints": 5,
                "autoRunPoints": 0,
                "vaultForceTotal": 0,
                "autoSwitchAtZero": false,
                "autoOwnershipPoints": 2,
                "foulPoints": 0,
                "rp": 0,
                "teleopOwnershipPoints": 0,
                "teleopSwitchForceSec": 0,
                "tba_gameData": "RRR",
                "teleopScaleBoostSec": 0,
                "autoRobot3": "None",
                "vaultPoints": 0,
                "vaultLevitatePlayed": 0,
                "autoQuestRankingPoint": false,
                "teleopPoints": 5
            }
        },
        "name": "score_breakdown"
    },
    {
        "size": 1520006760,
        "name": "predicted_time"
    },
    {
        "size": "blue",
        "name": "winning_alliance"
    },
    {
        "size": "qm",
        "name": "comp_level"
    },
    {
        "size": {
            "blue": {
                "team_keys": [
                    "frc1350",
                    "frc61",
                    "frc1519"
                ],
                "surrogate_team_keys": [],
                "dq_team_keys": [],
                "score": 394
            },
            "red": {
                "team_keys": [
                    "frc1786",
                    "frc1277",
                    "frc3466"
                ],
                "surrogate_team_keys": [],
                "dq_team_keys": [],
                "score": 7
            }
        },
        "name": "alliances"
    },
    {
        "size": 1520007660,
        "name": "time"
    },
    {
        "size": "2018mawor",
        "name": "event_key"
    },
    {
        "size": [
            {
                "key": "zFbysvLy46A",
                "type": "youtube"
            }
        ],
        "name": "videos"
    },
    {
        "size": "2018mawor_qm4",
        "name": "key"
    },
    {
        "size": 1,
        "name": "set_number"
    },
    {
        "size": 1519990653,
        "name": "actual_time"
    },
    {
        "size": 4,
        "name": "match_number"
    }
]
