{
    "set_number": 1,
    "time": 1520704320,
    "actual_time": 1520708927,
    "comp_level": "qm",
    "post_result_time": 1520709142,
    "videos": [],
    "score_breakdown": {
        "red": {
            "teleopSwitchForceSec": 0,
            "autoRobot1": "None",
            "teleopScaleOwnershipSec": 98,
            "vaultForcePlayed": 0,
            "vaultLevitateTotal": 3,
            "tba_gameData": "RLR",
            "endgameRobot3": "Parking",
            "teleopScaleForceSec": 0,
            "endgamePoints": 40,
            "autoRobot2": "AutoRun",
            "vaultLevitatePlayed": 3,
            "autoOwnershipPoints": 0,
            "foulCount": 6,
            "vaultPoints": 20,
            "teleopScaleBoostSec": 0,
            "totalPoints": 293,
            "vaultBoostPlayed": 1,
            "adjustPoints": 0,
            "autoQuestRankingPoint": false,
            "endgameRobot1": "Parking",
            "autoRunPoints": 5,
            "autoPoints": 5,
            "autoScaleOwnershipSec": 0,
            "foulPoints": 0,
            "teleopPoints": 288,
            "faceTheBossRankingPoint": false,
            "teleopSwitchOwnershipSec": 128,
            "techFoulCount": 0,
            "teleopOwnershipPoints": 228,
            "teleopSwitchBoostSec": 2,
            "rp": 2,
            "autoSwitchOwnershipSec": 0,
            "autoRobot3": "None",
            "vaultBoostTotal": 1,
            "endgameRobot2": "Levitate",
            "autoSwitchAtZero": false,
            "vaultForceTotal": 0
        },
        "blue": {
            "teleopSwitchForceSec": 0,
            "autoRobot1": "None",
            "teleopScaleOwnershipSec": 20,
            "vaultForcePlayed": 0,
            "vaultLevitateTotal": 3,
            "tba_gameData": "RLR",
            "endgameRobot3": "Levitate",
            "teleopScaleForceSec": 0,
            "endgamePoints": 40,
            "autoRobot2": "AutoRun",
            "vaultLevitatePlayed": 3,
            "autoOwnershipPoints": 0,
            "foulCount": 0,
            "vaultPoints": 15,
            "teleopScaleBoostSec": 0,
            "totalPoints": 194,
            "vaultBoostPlayed": 0,
            "adjustPoints": 0,
            "autoQuestRankingPoint": false,
            "endgameRobot1": "Parking",
            "autoRunPoints": 10,
            "autoPoints": 10,
            "autoScaleOwnershipSec": 0,
            "foulPoints": 30,
            "teleopPoints": 154,
            "faceTheBossRankingPoint": false,
            "teleopSwitchOwnershipSec": 79,
            "techFoulCount": 0,
            "teleopOwnershipPoints": 99,
            "teleopSwitchBoostSec": 0,
            "rp": 0,
            "autoSwitchOwnershipSec": 0,
            "autoRobot3": "AutoRun",
            "vaultBoostTotal": 0,
            "endgameRobot2": "Parking",
            "autoSwitchAtZero": false,
            "vaultForceTotal": 0
        }
    },
    "key": "2018njfla_qm17",
    "predicted_time": 1520709063,
    "match_number": 17,
    "winning_alliance": "red",
    "alliances": {
        "red": {
            "team_keys": [
                "frc1089",
                "frc1672",
                "frc4652"
            ],
            "dq_team_keys": [],
            "surrogate_team_keys": [],
            "score": 293
        },
        "blue": {
            "team_keys": [
                "frc11",
                "frc4575",
                "frc6016"
            ],
            "dq_team_keys": [],
            "surrogate_team_keys": [],
            "score": 194
        }
    },
    "event_key": "2018njfla"
}