[
    {
        "size": 1520705470,
        "name": "actual_time"
    },
    {
        "size": {
            "red": {
                "score": 192,
                "team_keys": [
                    "frc5000",
                    "frc4176",
                    "frc23"
                ],
                "dq_team_keys": [],
                "surrogate_team_keys": []
            },
            "blue": {
                "score": 270,
                "team_keys": [
                    "frc121",
                    "frc5422",
                    "frc2168"
                ],
                "dq_team_keys": [],
                "surrogate_team_keys": []
            }
        },
        "name": "alliances"
    },
    {
        "size": "blue",
        "name": "winning_alliance"
    },
    {
        "size": 1,
        "name": "set_number"
    },
    {
        "size": 1520705634,
        "name": "post_result_time"
    },
    {
        "size": 16,
        "name": "match_number"
    },
    {
        "size": "2018mabri",
        "name": "event_key"
    },
    {
        "size": 1520705465,
        "name": "predicted_time"
    },
    {
        "size": "2018mabri_qm16",
        "name": "key"
    },
    {
        "size": [],
        "name": "videos"
    },
    {
        "size": {
            "red": {
                "autoRunPoints": 10,
                "rp": 0,
                "teleopScaleOwnershipSec": 2,
                "vaultLevitatePlayed": 0,
                "autoScaleOwnershipSec": 0,
                "teleopPoints": 168,
                "techFoulCount": 0,
                "vaultForcePlayed": 0,
                "vaultBoostTotal": 0,
                "teleopOwnershipPoints": 138,
                "teleopSwitchBoostSec": 0,
                "endgameRobot2": "None",
                "foulPoints": 0,
                "autoRobot1": "AutoRun",
                "faceTheBossRankingPoint": false,
                "autoOwnershipPoints": 14,
                "autoRobot2": "None",
                "endgameRobot1": "Climbing",
                "autoSwitchAtZero": true,
                "tba_gameData": "RLR",
                "autoQuestRankingPoint": false,
                "teleopSwitchForceSec": 0,
                "vaultForceTotal": 0,
                "vaultLevitateTotal": 0,
                "teleopSwitchOwnershipSec": 136,
                "autoPoints": 24,
                "vaultPoints": 0,
                "totalPoints": 192,
                "vaultBoostPlayed": 0,
                "adjustPoints": 0,
                "teleopScaleBoostSec": 0,
                "teleopScaleForceSec": 0,
                "foulCount": 2,
                "autoSwitchOwnershipSec": 7,
                "autoRobot3": "AutoRun",
                "endgameRobot3": "None",
                "endgamePoints": 30
            },
            "blue": {
                "autoRunPoints": 15,
                "rp": 2,
                "teleopScaleOwnershipSec": 107,
                "vaultLevitatePlayed": 0,
                "autoScaleOwnershipSec": 0,
                "teleopPoints": 245,
                "techFoulCount": 0,
                "vaultForcePlayed": 0,
                "vaultBoostTotal": 0,
                "teleopOwnershipPoints": 240,
                "teleopSwitchBoostSec": 0,
                "endgameRobot2": "None",
                "foulPoints": 10,
                "autoRobot1": "AutoRun",
                "faceTheBossRankingPoint": false,
                "autoOwnershipPoints": 0,
                "autoRobot2": "AutoRun",
                "endgameRobot1": "Parking",
                "autoSwitchAtZero": false,
                "tba_gameData": "RLR",
                "autoQuestRankingPoint": false,
                "teleopSwitchForceSec": 0,
                "vaultForceTotal": 0,
                "vaultLevitateTotal": 0,
                "teleopSwitchOwnershipSec": 133,
                "autoPoints": 15,
                "vaultPoints": 0,
                "totalPoints": 270,
                "vaultBoostPlayed": 0,
                "adjustPoints": 0,
                "teleopScaleBoostSec": 0,
                "teleopScaleForceSec": 0,
                "foulCount": 0,
                "autoSwitchOwnershipSec": 0,
                "autoRobot3": "AutoRun",
                "endgameRobot3": "None",
                "endgamePoints": 5
            }
        },
        "name": "score_breakdown"
    },
    {
        "size": "qm",
        "name": "comp_level"
    },
    {
        "size": 1520703900,
        "name": "time"
    }
]
