[
    {
        "size": 1518878703,
        "name": "actual_time"
    },
    {
        "size": 1518878847,
        "name": "predicted_time"
    },
    {
        "size": "2018week0_qm3",
        "name": "key"
    },
    {
        "size": {
            "blue": {
                "foulPoints": 5,
                "autoPoints": 15,
                "autoRobot3": "AutoRun",
                "autoSwitchOwnershipSec": 0,
                "vaultPoints": 15,
                "vaultBoostTotal": 0,
                "teleopSwitchOwnershipSec": 123,
                "techFoulCount": 1,
                "autoRunPoints": 15,
                "teleopScaleBoostSec": 0,
                "vaultLevitatePlayed": 0,
                "endgamePoints": 0,
                "teleopOwnershipPoints": 175,
                "vaultBoostPlayed": 0,
                "endgameRobot2": "None",
                "rp": 2,
                "teleopSwitchForceSec": 0,
                "foulCount": 0,
                "autoQuestRankingPoint": false,
                "autoScaleOwnershipSec": 0,
                "autoRobot1": "AutoRun",
                "teleopSwitchBoostSec": 0,
                "vaultForcePlayed": 0,
                "autoOwnershipPoints": 0,
                "autoRobot2": "AutoRun",
                "endgameRobot1": "None",
                "teleopScaleOwnershipSec": 52,
                "endgameRobot3": "None",
                "totalPoints": 210,
                "vaultForceTotal": 0,
                "adjustPoints": 0,
                "faceTheBossRankingPoint": false,
                "teleopPoints": 190,
                "tba_gameData": "RRR",
                "autoSwitchAtZero": false,
                "teleopScaleForceSec": 0,
                "vaultLevitateTotal": 3
            },
            "red": {
                "foulPoints": 25,
                "autoPoints": 5,
                "autoRobot3": "None",
                "autoSwitchOwnershipSec": 0,
                "vaultPoints": 5,
                "vaultBoostTotal": 0,
                "teleopSwitchOwnershipSec": 123,
                "techFoulCount": 0,
                "autoRunPoints": 5,
                "teleopScaleBoostSec": 0,
                "vaultLevitatePlayed": 0,
                "endgamePoints": 0,
                "teleopOwnershipPoints": 147,
                "vaultBoostPlayed": 0,
                "endgameRobot2": "None",
                "rp": 0,
                "teleopSwitchForceSec": 5,
                "foulCount": 1,
                "autoQuestRankingPoint": false,
                "autoScaleOwnershipSec": 0,
                "autoRobot1": "None",
                "teleopSwitchBoostSec": 0,
                "vaultForcePlayed": 1,
                "autoOwnershipPoints": 0,
                "autoRobot2": "AutoRun",
                "endgameRobot1": "None",
                "teleopScaleOwnershipSec": 24,
                "endgameRobot3": "None",
                "totalPoints": 182,
                "vaultForceTotal": 1,
                "adjustPoints": 0,
                "faceTheBossRankingPoint": false,
                "teleopPoints": 152,
                "tba_gameData": "RRR",
                "autoSwitchAtZero": false,
                "teleopScaleForceSec": 0,
                "vaultLevitateTotal": 0
            }
        },
        "name": "score_breakdown"
    },
    {
        "size": 1518878895,
        "name": "post_result_time"
    },
    {
        "size": "2018week0",
        "name": "event_key"
    },
    {
        "size": "blue",
        "name": "winning_alliance"
    },
    {
        "size": 3,
        "name": "match_number"
    },
    {
        "size": [
            {
                "type": "youtube",
                "key": "3rZvT-JCUto"
            }
        ],
        "name": "videos"
    },
    {
        "size": {
            "blue": {
                "team_keys": [
                    "frc5813",
                    "frc2342",
                    "frc3236"
                ],
                "score": 210,
                "surrogate_team_keys": [],
                "dq_team_keys": []
            },
            "red": {
                "team_keys": [
                    "frc238",
                    "frc6153",
                    "frc4909"
                ],
                "score": 182,
                "surrogate_team_keys": [],
                "dq_team_keys": []
            }
        },
        "name": "alliances"
    },
    {
        "size": 1518877080,
        "name": "time"
    },
    {
        "size": 1,
        "name": "set_number"
    },
    {
        "size": "qm",
        "name": "comp_level"
    }
]
