{
    "set_number": 1,
    "time": 1520025660,
    "actual_time": 1520008172,
    "comp_level": "qm",
    "post_result_time": 1520008348,
    "videos": [],
    "score_breakdown": {
        "red": {
            "teleopSwitchForceSec": 0,
            "autoRobot1": "AutoRun",
            "teleopScaleOwnershipSec": 103,
            "vaultForcePlayed": 0,
            "vaultLevitateTotal": 3,
            "tba_gameData": "LRL",
            "endgameRobot3": "None",
            "teleopScaleForceSec": 0,
            "endgamePoints": 60,
            "autoRobot2": "AutoRun",
            "vaultLevitatePlayed": 3,
            "autoOwnershipPoints": 18,
            "foulCount": 1,
            "vaultPoints": 30,
            "teleopScaleBoostSec": 10,
            "totalPoints": 367,
            "vaultBoostPlayed": 2,
            "adjustPoints": 0,
            "autoQuestRankingPoint": false,
            "endgameRobot1": "Levitate",
            "autoRunPoints": 10,
            "autoPoints": 28,
            "autoScaleOwnershipSec": 0,
            "foulPoints": 0,
            "teleopPoints": 339,
            "faceTheBossRankingPoint": false,
            "teleopSwitchOwnershipSec": 136,
            "techFoulCount": 0,
            "teleopOwnershipPoints": 249,
            "teleopSwitchBoostSec": 0,
            "rp": 2,
            "autoSwitchOwnershipSec": 9,
            "autoRobot3": "None",
            "vaultBoostTotal": 3,
            "endgameRobot2": "Climbing",
            "autoSwitchAtZero": true,
            "vaultForceTotal": 0
        },
        "blue": {
            "teleopSwitchForceSec": 1,
            "autoRobot1": "AutoRun",
            "teleopScaleOwnershipSec": 7,
            "vaultForcePlayed": 1,
            "vaultLevitateTotal": 3,
            "tba_gameData": "LRL",
            "endgameRobot3": "Parking",
            "teleopScaleForceSec": 0,
            "endgamePoints": 40,
            "autoRobot2": "None",
            "vaultLevitatePlayed": 3,
            "autoOwnershipPoints": 0,
            "foulCount": 0,
            "vaultPoints": 25,
            "teleopScaleBoostSec": 0,
            "totalPoints": 229,
            "vaultBoostPlayed": 1,
            "adjustPoints": 0,
            "autoQuestRankingPoint": false,
            "endgameRobot1": "Levitate",
            "autoRunPoints": 10,
            "autoPoints": 10,
            "autoScaleOwnershipSec": 0,
            "foulPoints": 5,
            "teleopPoints": 214,
            "faceTheBossRankingPoint": false,
            "teleopSwitchOwnershipSec": 132,
            "techFoulCount": 0,
            "teleopOwnershipPoints": 149,
            "teleopSwitchBoostSec": 10,
            "rp": 0,
            "autoSwitchOwnershipSec": 0,
            "autoRobot3": "AutoRun",
            "vaultBoostTotal": 1,
            "endgameRobot2": "Parking",
            "autoSwitchAtZero": false,
            "vaultForceTotal": 1
        }
    },
    "key": "2018mxmo_qm46",
    "predicted_time": 1520025274,
    "match_number": 46,
    "winning_alliance": "red",
    "alliances": {
        "red": {
            "team_keys": [
                "frc7102",
                "frc3478",
                "frc6319"
            ],
            "dq_team_keys": [],
            "surrogate_team_keys": [],
            "score": 367
        },
        "blue": {
            "team_keys": [
                "frc3354",
                "frc6156",
                "frc6694"
            ],
            "dq_team_keys": [],
            "surrogate_team_keys": [],
            "score": 229
        }
    },
    "event_key": "2018mxmo"
}