[
    {
        "size": 1520100289,
        "name": "post_result_time"
    },
    {
        "size": {
            "blue": {
                "foulCount": 1,
                "vaultBoostTotal": 0,
                "faceTheBossRankingPoint": false,
                "endgameRobot2": "Levitate",
                "teleopScaleForceSec": 10,
                "autoRobot2": "AutoRun",
                "teleopSwitchBoostSec": 0,
                "techFoulCount": 2,
                "teleopSwitchOwnershipSec": 129,
                "autoScaleOwnershipSec": 0,
                "autoRobot1": "AutoRun",
                "autoSwitchOwnershipSec": 0,
                "vaultLevitateTotal": 3,
                "vaultBoostPlayed": 0,
                "endgameRobot3": "Parking",
                "autoPoints": 15,
                "adjustPoints": 0,
                "teleopScaleOwnershipSec": 13,
                "totalPoints": 277,
                "vaultForcePlayed": 2,
                "endgameRobot1": "Climbing",
                "endgamePoints": 65,
                "autoRunPoints": 15,
                "vaultForceTotal": 2,
                "autoSwitchAtZero": false,
                "autoOwnershipPoints": 0,
                "foulPoints": 30,
                "rp": 0,
                "teleopOwnershipPoints": 142,
                "teleopSwitchForceSec": 0,
                "tba_gameData": "LLL",
                "teleopScaleBoostSec": 0,
                "autoRobot3": "AutoRun",
                "vaultPoints": 25,
                "vaultLevitatePlayed": 3,
                "autoQuestRankingPoint": false,
                "teleopPoints": 232
            },
            "red": {
                "foulCount": 1,
                "vaultBoostTotal": 0,
                "faceTheBossRankingPoint": true,
                "endgameRobot2": "Levitate",
                "teleopScaleForceSec": 0,
                "autoRobot2": "AutoRun",
                "teleopSwitchBoostSec": 0,
                "techFoulCount": 1,
                "teleopSwitchOwnershipSec": 122,
                "autoScaleOwnershipSec": 0,
                "autoRobot1": "AutoRun",
                "autoSwitchOwnershipSec": 0,
                "vaultLevitateTotal": 3,
                "vaultBoostPlayed": 0,
                "endgameRobot3": "Climbing",
                "autoPoints": 10,
                "adjustPoints": 0,
                "teleopScaleOwnershipSec": 100,
                "totalPoints": 392,
                "vaultForcePlayed": 0,
                "endgameRobot1": "Climbing",
                "endgamePoints": 90,
                "autoRunPoints": 10,
                "vaultForceTotal": 0,
                "autoSwitchAtZero": false,
                "autoOwnershipPoints": 0,
                "foulPoints": 55,
                "rp": 3,
                "teleopOwnershipPoints": 222,
                "teleopSwitchForceSec": 0,
                "tba_gameData": "LLL",
                "teleopScaleBoostSec": 0,
                "autoRobot3": "None",
                "vaultPoints": 15,
                "vaultLevitatePlayed": 3,
                "autoQuestRankingPoint": false,
                "teleopPoints": 327
            }
        },
        "name": "score_breakdown"
    },
    {
        "size": 1520254327,
        "name": "predicted_time"
    },
    {
        "size": "red",
        "name": "winning_alliance"
    },
    {
        "size": "qm",
        "name": "comp_level"
    },
    {
        "size": {
            "blue": {
                "team_keys": [
                    "frc1246",
                    "frc4939",
                    "frc6975"
                ],
                "surrogate_team_keys": [],
                "dq_team_keys": [],
                "score": 277
            },
            "red": {
                "team_keys": [
                    "frc5911",
                    "frc2200",
                    "frc6866"
                ],
                "surrogate_team_keys": [],
                "dq_team_keys": [],
                "score": 392
            }
        },
        "name": "alliances"
    },
    {
        "size": 1520116080,
        "name": "time"
    },
    {
        "size": "2018onosh",
        "name": "event_key"
    },
    {
        "size": [],
        "name": "videos"
    },
    {
        "size": "2018onosh_qm45",
        "name": "key"
    },
    {
        "size": 1,
        "name": "set_number"
    },
    {
        "size": 1520100007,
        "name": "actual_time"
    },
    {
        "size": 45,
        "name": "match_number"
    }
]
