{
    "alliances": {
        "red": {
            "score": 257,
            "team_keys": [
                "frc1868",
                "frc7173",
                "frc5078"
            ],
            "surrogate_team_keys": [],
            "dq_team_keys": []
        },
        "blue": {
            "score": 416,
            "team_keys": [
                "frc1241",
                "frc7158",
                "frc6403"
            ],
            "surrogate_team_keys": [],
            "dq_team_keys": []
        }
    },
    "comp_level": "qm",
    "event_key": "2018bcvi",
    "score_breakdown": {
        "red": {
            "foulPoints": 0,
            "autoRunPoints": 10,
            "teleopScaleOwnershipSec": 11,
            "autoOwnershipPoints": 0,
            "endgameRobot3": "Climbing",
            "autoScaleOwnershipSec": 0,
            "teleopScaleBoostSec": 0,
            "teleopSwitchForceSec": 0,
            "endgameRobot1": "Levitate",
            "endgameRobot2": "Parking",
            "tba_gameData": "LRL",
            "foulCount": 0,
            "vaultLevitatePlayed": 3,
            "autoSwitchAtZero": false,
            "teleopSwitchOwnershipSec": 121,
            "vaultBoostTotal": 3,
            "autoPoints": 10,
            "endgamePoints": 65,
            "teleopScaleForceSec": 10,
            "autoRobot1": "None",
            "vaultForceTotal": 2,
            "teleopOwnershipPoints": 142,
            "adjustPoints": 0,
            "autoRobot3": "AutoRun",
            "autoQuestRankingPoint": false,
            "totalPoints": 257,
            "autoSwitchOwnershipSec": 0,
            "vaultForcePlayed": 2,
            "techFoulCount": 1,
            "rp": 0,
            "vaultBoostPlayed": 3,
            "autoRobot2": "AutoRun",
            "vaultPoints": 40,
            "vaultLevitateTotal": 3,
            "teleopSwitchBoostSec": 10,
            "faceTheBossRankingPoint": false,
            "teleopPoints": 247
        },
        "blue": {
            "foulPoints": 25,
            "autoRunPoints": 15,
            "teleopScaleOwnershipSec": 116,
            "autoOwnershipPoints": 24,
            "endgameRobot3": "None",
            "autoScaleOwnershipSec": 0,
            "teleopScaleBoostSec": 10,
            "teleopSwitchForceSec": 10,
            "endgameRobot1": "Parking",
            "endgameRobot2": "Levitate",
            "tba_gameData": "LRL",
            "foulCount": 0,
            "vaultLevitatePlayed": 3,
            "autoSwitchAtZero": true,
            "teleopSwitchOwnershipSec": 136,
            "vaultBoostTotal": 3,
            "autoPoints": 39,
            "endgamePoints": 35,
            "teleopScaleForceSec": 10,
            "autoRobot1": "AutoRun",
            "vaultForceTotal": 3,
            "teleopOwnershipPoints": 272,
            "adjustPoints": 0,
            "autoRobot3": "AutoRun",
            "autoQuestRankingPoint": true,
            "totalPoints": 416,
            "autoSwitchOwnershipSec": 12,
            "vaultForcePlayed": 3,
            "techFoulCount": 0,
            "rp": 3,
            "vaultBoostPlayed": 3,
            "autoRobot2": "AutoRun",
            "vaultPoints": 45,
            "vaultLevitateTotal": 3,
            "teleopSwitchBoostSec": 10,
            "faceTheBossRankingPoint": false,
            "teleopPoints": 352
        }
    },
    "key": "2018bcvi_qm52",
    "post_result_time": 1521218730,
    "set_number": 1,
    "predicted_time": 1521218628,
    "actual_time": 1521218564,
    "time": 1521219240,
    "match_number": 52,
    "winning_alliance": "blue",
    "videos": []
}