{
    "set_number": 1,
    "time": 1520092320,
    "actual_time": 1520092150,
    "comp_level": "qm",
    "post_result_time": 1520092436,
    "videos": [
        {
            "type": "youtube",
            "key": "_s0gBd8u7N4"
        },
        {
            "type": "youtube",
            "key": "5S1vdttkm0Y"
        }
    ],
    "score_breakdown": {
        "red": {
            "teleopSwitchForceSec": 0,
            "autoRobot1": "AutoRun",
            "teleopScaleOwnershipSec": 25,
            "vaultForcePlayed": 0,
            "vaultLevitateTotal": 2,
            "tba_gameData": "RLR",
            "endgameRobot3": "None",
            "teleopScaleForceSec": 0,
            "endgamePoints": 10,
            "autoRobot2": "AutoRun",
            "vaultLevitatePlayed": 0,
            "autoOwnershipPoints": 30,
            "foulCount": 1,
            "vaultPoints": 10,
            "teleopScaleBoostSec": 0,
            "totalPoints": 194,
            "vaultBoostPlayed": 0,
            "adjustPoints": 0,
            "autoQuestRankingPoint": true,
            "endgameRobot1": "Parking",
            "autoRunPoints": 15,
            "autoPoints": 45,
            "autoScaleOwnershipSec": 8,
            "foulPoints": 0,
            "teleopPoints": 149,
            "faceTheBossRankingPoint": false,
            "teleopSwitchOwnershipSec": 104,
            "techFoulCount": 0,
            "teleopOwnershipPoints": 129,
            "teleopSwitchBoostSec": 0,
            "rp": 1,
            "autoSwitchOwnershipSec": 7,
            "autoRobot3": "AutoRun",
            "vaultBoostTotal": 0,
            "endgameRobot2": "Parking",
            "autoSwitchAtZero": true,
            "vaultForceTotal": 0
        },
        "blue": {
            "teleopSwitchForceSec": 0,
            "autoRobot1": "AutoRun",
            "teleopScaleOwnershipSec": 96,
            "vaultForcePlayed": 0,
            "vaultLevitateTotal": 3,
            "tba_gameData": "RLR",
            "endgameRobot3": "Climbing",
            "teleopScaleForceSec": 0,
            "endgamePoints": 90,
            "autoRobot2": "AutoRun",
            "vaultLevitatePlayed": 3,
            "autoOwnershipPoints": 24,
            "foulCount": 0,
            "vaultPoints": 30,
            "teleopScaleBoostSec": 10,
            "totalPoints": 416,
            "vaultBoostPlayed": 3,
            "adjustPoints": 0,
            "autoQuestRankingPoint": true,
            "endgameRobot1": "Climbing",
            "autoRunPoints": 15,
            "autoPoints": 39,
            "autoScaleOwnershipSec": 0,
            "foulPoints": 5,
            "teleopPoints": 372,
            "faceTheBossRankingPoint": true,
            "teleopSwitchOwnershipSec": 136,
            "techFoulCount": 0,
            "teleopOwnershipPoints": 252,
            "teleopSwitchBoostSec": 10,
            "rp": 4,
            "autoSwitchOwnershipSec": 12,
            "autoRobot3": "AutoRun",
            "vaultBoostTotal": 3,
            "endgameRobot2": "Levitate",
            "autoSwitchAtZero": true,
            "vaultForceTotal": 0
        }
    },
    "key": "2018qcmo_qm74",
    "predicted_time": 1520092261,
    "match_number": 74,
    "winning_alliance": "blue",
    "alliances": {
        "red": {
            "team_keys": [
                "frc6847",
                "frc3986",
                "frc3386"
            ],
            "dq_team_keys": [],
            "surrogate_team_keys": [],
            "score": 194
        },
        "blue": {
            "team_keys": [
                "frc3990",
                "frc3379",
                "frc4955"
            ],
            "dq_team_keys": [],
            "surrogate_team_keys": [],
            "score": 416
        }
    },
    "event_key": "2018qcmo"
}