{
    "set_number": 1,
    "time": 1520612460,
    "actual_time": 1520613914,
    "comp_level": "qm",
    "post_result_time": 1520614115,
    "videos": [
        {
            "type": "youtube",
            "key": "SnuiDLfwnaE"
        }
    ],
    "score_breakdown": {
        "red": {
            "teleopSwitchForceSec": 10,
            "autoRobot1": "None",
            "teleopScaleOwnershipSec": 136,
            "vaultForcePlayed": 3,
            "vaultLevitateTotal": 3,
            "tba_gameData": "LRL",
            "endgameRobot3": "Levitate",
            "teleopScaleForceSec": 10,
            "endgamePoints": 90,
            "autoRobot2": "AutoRun",
            "vaultLevitatePlayed": 3,
            "autoOwnershipPoints": 34,
            "foulCount": 0,
            "vaultPoints": 45,
            "teleopScaleBoostSec": 10,
            "totalPoints": 471,
            "vaultBoostPlayed": 3,
            "adjustPoints": 0,
            "autoQuestRankingPoint": false,
            "endgameRobot1": "Climbing",
            "autoRunPoints": 10,
            "autoPoints": 44,
            "autoScaleOwnershipSec": 8,
            "foulPoints": 0,
            "teleopPoints": 427,
            "faceTheBossRankingPoint": true,
            "teleopSwitchOwnershipSec": 136,
            "techFoulCount": 2,
            "teleopOwnershipPoints": 292,
            "teleopSwitchBoostSec": 10,
            "rp": 3,
            "autoSwitchOwnershipSec": 9,
            "autoRobot3": "AutoRun",
            "vaultBoostTotal": 3,
            "endgameRobot2": "Climbing",
            "autoSwitchAtZero": true,
            "vaultForceTotal": 3
        },
        "blue": {
            "teleopSwitchForceSec": 0,
            "autoRobot1": "AutoRun",
            "teleopScaleOwnershipSec": 0,
            "vaultForcePlayed": 0,
            "vaultLevitateTotal": 1,
            "tba_gameData": "LRL",
            "endgameRobot3": "Parking",
            "teleopScaleForceSec": 0,
            "endgamePoints": 10,
            "autoRobot2": "AutoRun",
            "vaultLevitatePlayed": 0,
            "autoOwnershipPoints": 0,
            "foulCount": 0,
            "vaultPoints": 5,
            "teleopScaleBoostSec": 0,
            "totalPoints": 75,
            "vaultBoostPlayed": 0,
            "adjustPoints": 0,
            "autoQuestRankingPoint": false,
            "endgameRobot1": "None",
            "autoRunPoints": 10,
            "autoPoints": 10,
            "autoScaleOwnershipSec": 0,
            "foulPoints": 50,
            "teleopPoints": 15,
            "faceTheBossRankingPoint": false,
            "teleopSwitchOwnershipSec": 0,
            "techFoulCount": 0,
            "teleopOwnershipPoints": 0,
            "teleopSwitchBoostSec": 0,
            "rp": 0,
            "autoSwitchOwnershipSec": 0,
            "autoRobot3": "None",
            "vaultBoostTotal": 0,
            "endgameRobot2": "Parking",
            "autoSwitchAtZero": false,
            "vaultForceTotal": 0
        }
    },
    "key": "2018misjo_qm4",
    "predicted_time": 1520613945,
    "match_number": 4,
    "winning_alliance": "red",
    "alliances": {
        "red": {
            "team_keys": [
                "frc2337",
                "frc2767",
                "frc85"
            ],
            "dq_team_keys": [],
            "surrogate_team_keys": [],
            "score": 471
        },
        "blue": {
            "team_keys": [
                "frc5610",
                "frc6627",
                "frc3658"
            ],
            "dq_team_keys": [],
            "surrogate_team_keys": [],
            "score": 75
        }
    },
    "event_key": "2018misjo"
}