{
    "match_number": 3,
    "alliances": {
        "blue": {
            "dq_team_keys": [],
            "team_keys": [
                "frc1114",
                "frc6917",
                "frc6162"
            ],
            "surrogate_team_keys": [],
            "score": 434
        },
        "red": {
            "dq_team_keys": [],
            "team_keys": [
                "frc6866",
                "frc4308",
                "frc7136"
            ],
            "surrogate_team_keys": [],
            "score": 159
        }
    },
    "videos": [],
    "winning_alliance": "blue",
    "event_key": "2018onto1",
    "predicted_time": 1521222122,
    "comp_level": "qm",
    "key": "2018onto1_qm3",
    "actual_time": 1521197656,
    "time": 1521211440,
    "post_result_time": 1521197842,
    "set_number": 1,
    "score_breakdown": {
        "blue": {
            "faceTheBossRankingPoint": false,
            "teleopOwnershipPoints": 272,
            "endgameRobot2": "None",
            "teleopScaleBoostSec": 10,
            "autoRobot3": "None",
            "tba_gameData": "RLR",
            "vaultForcePlayed": 0,
            "autoScaleOwnershipSec": 0,
            "vaultBoostPlayed": 3,
            "autoRunPoints": 10,
            "teleopScaleForceSec": 0,
            "foulPoints": 30,
            "teleopScaleOwnershipSec": 116,
            "vaultLevitatePlayed": 3,
            "vaultLevitateTotal": 3,
            "endgamePoints": 60,
            "endgameRobot3": "Levitate",
            "teleopSwitchOwnershipSec": 136,
            "vaultPoints": 40,
            "techFoulCount": 0,
            "autoSwitchAtZero": true,
            "autoPoints": 32,
            "totalPoints": 434,
            "adjustPoints": 0,
            "autoRobot1": "AutoRun",
            "autoOwnershipPoints": 22,
            "teleopPoints": 372,
            "endgameRobot1": "Climbing",
            "teleopSwitchForceSec": 0,
            "teleopSwitchBoostSec": 10,
            "autoSwitchOwnershipSec": 11,
            "foulCount": 0,
            "rp": 2,
            "autoRobot2": "AutoRun",
            "vaultForceTotal": 2,
            "autoQuestRankingPoint": false,
            "vaultBoostTotal": 3
        },
        "red": {
            "faceTheBossRankingPoint": false,
            "teleopOwnershipPoints": 76,
            "endgameRobot2": "Parking",
            "teleopScaleBoostSec": 0,
            "autoRobot3": "None",
            "tba_gameData": "RLR",
            "vaultForcePlayed": 2,
            "autoScaleOwnershipSec": 0,
            "vaultBoostPlayed": 0,
            "autoRunPoints": 10,
            "teleopScaleForceSec": 10,
            "foulPoints": 0,
            "teleopScaleOwnershipSec": 11,
            "vaultLevitatePlayed": 3,
            "vaultLevitateTotal": 3,
            "endgamePoints": 40,
            "endgameRobot3": "Levitate",
            "teleopSwitchOwnershipSec": 65,
            "vaultPoints": 25,
            "techFoulCount": 0,
            "autoSwitchAtZero": true,
            "autoPoints": 18,
            "totalPoints": 159,
            "adjustPoints": 0,
            "autoRobot1": "AutoRun",
            "autoOwnershipPoints": 8,
            "teleopPoints": 141,
            "endgameRobot1": "Parking",
            "teleopSwitchForceSec": 0,
            "teleopSwitchBoostSec": 0,
            "autoSwitchOwnershipSec": 4,
            "foulCount": 6,
            "rp": 0,
            "autoRobot2": "AutoRun",
            "vaultForceTotal": 2,
            "autoQuestRankingPoint": false,
            "vaultBoostTotal": 0
        }
    }
}