{
    "match_number": 59,
    "alliances": {
        "blue": {
            "dq_team_keys": [],
            "team_keys": [
                "frc4308",
                "frc6544",
                "frc854"
            ],
            "surrogate_team_keys": [],
            "score": 358
        },
        "red": {
            "dq_team_keys": [],
            "team_keys": [
                "frc5596",
                "frc6878",
                "frc5719"
            ],
            "surrogate_team_keys": [],
            "score": 152
        }
    },
    "videos": [],
    "winning_alliance": "blue",
    "event_key": "2018onto1",
    "predicted_time": 1521290834,
    "comp_level": "qm",
    "key": "2018onto1_qm59",
    "actual_time": 1521290940,
    "time": 1521238560,
    "post_result_time": 1521291113,
    "set_number": 1,
    "score_breakdown": {
        "blue": {
            "faceTheBossRankingPoint": false,
            "teleopOwnershipPoints": 259,
            "endgameRobot2": "Parking",
            "teleopScaleBoostSec": 10,
            "autoRobot3": "AutoRun",
            "tba_gameData": "RLR",
            "vaultForcePlayed": 0,
            "autoScaleOwnershipSec": 0,
            "vaultBoostPlayed": 2,
            "autoRunPoints": 15,
            "teleopScaleForceSec": 0,
            "foulPoints": 0,
            "teleopScaleOwnershipSec": 113,
            "vaultLevitatePlayed": 3,
            "vaultLevitateTotal": 3,
            "endgamePoints": 35,
            "endgameRobot3": "Levitate",
            "teleopSwitchOwnershipSec": 136,
            "vaultPoints": 35,
            "techFoulCount": 1,
            "autoSwitchAtZero": true,
            "autoPoints": 29,
            "totalPoints": 358,
            "adjustPoints": 0,
            "autoRobot1": "AutoRun",
            "autoOwnershipPoints": 14,
            "teleopPoints": 329,
            "endgameRobot1": "None",
            "teleopSwitchForceSec": 0,
            "teleopSwitchBoostSec": 0,
            "autoSwitchOwnershipSec": 7,
            "foulCount": 1,
            "rp": 3,
            "autoRobot2": "AutoRun",
            "vaultForceTotal": 1,
            "autoQuestRankingPoint": true,
            "vaultBoostTotal": 3
        },
        "red": {
            "faceTheBossRankingPoint": false,
            "teleopOwnershipPoints": 22,
            "endgameRobot2": "Levitate",
            "teleopScaleBoostSec": 0,
            "autoRobot3": "AutoRun",
            "tba_gameData": "RLR",
            "vaultForcePlayed": 3,
            "autoScaleOwnershipSec": 0,
            "vaultBoostPlayed": 3,
            "autoRunPoints": 15,
            "teleopScaleForceSec": 10,
            "foulPoints": 30,
            "teleopScaleOwnershipSec": 11,
            "vaultLevitatePlayed": 3,
            "vaultLevitateTotal": 3,
            "endgamePoints": 40,
            "endgameRobot3": "Parking",
            "teleopSwitchOwnershipSec": 11,
            "vaultPoints": 45,
            "techFoulCount": 0,
            "autoSwitchAtZero": false,
            "autoPoints": 15,
            "totalPoints": 152,
            "adjustPoints": 0,
            "autoRobot1": "AutoRun",
            "autoOwnershipPoints": 0,
            "teleopPoints": 107,
            "endgameRobot1": "Parking",
            "teleopSwitchForceSec": 10,
            "teleopSwitchBoostSec": 0,
            "autoSwitchOwnershipSec": 0,
            "foulCount": 0,
            "rp": 0,
            "autoRobot2": "AutoRun",
            "vaultForceTotal": 3,
            "autoQuestRankingPoint": false,
            "vaultBoostTotal": 3
        }
    }
}