[
    {
        "size": 1520116809,
        "name": "post_result_time"
    },
    {
        "size": {
            "blue": {
                "foulCount": 0,
                "vaultBoostTotal": 0,
                "faceTheBossRankingPoint": false,
                "endgameRobot2": "None",
                "teleopScaleForceSec": 0,
                "autoRobot2": "None",
                "teleopSwitchBoostSec": 0,
                "techFoulCount": 0,
                "teleopSwitchOwnershipSec": 0,
                "autoScaleOwnershipSec": 0,
                "autoRobot1": "AutoRun",
                "autoSwitchOwnershipSec": 0,
                "vaultLevitateTotal": 1,
                "vaultBoostPlayed": 0,
                "endgameRobot3": "Parking",
                "autoPoints": 10,
                "adjustPoints": 0,
                "teleopScaleOwnershipSec": 0,
                "totalPoints": 25,
                "vaultForcePlayed": 0,
                "endgameRobot1": "None",
                "endgamePoints": 5,
                "autoRunPoints": 10,
                "vaultForceTotal": 0,
                "autoSwitchAtZero": false,
                "autoOwnershipPoints": 0,
                "foulPoints": 5,
                "rp": 0,
                "teleopOwnershipPoints": 0,
                "teleopSwitchForceSec": 0,
                "tba_gameData": "RLR",
                "teleopScaleBoostSec": 0,
                "autoRobot3": "AutoRun",
                "vaultPoints": 5,
                "vaultLevitatePlayed": 0,
                "autoQuestRankingPoint": false,
                "teleopPoints": 10
            },
            "red": {
                "foulCount": 1,
                "vaultBoostTotal": 3,
                "faceTheBossRankingPoint": false,
                "endgameRobot2": "Climbing",
                "teleopScaleForceSec": 10,
                "autoRobot2": "AutoRun",
                "teleopSwitchBoostSec": 10,
                "techFoulCount": 0,
                "teleopSwitchOwnershipSec": 136,
                "autoScaleOwnershipSec": 9,
                "autoRobot1": "AutoRun",
                "autoSwitchOwnershipSec": 5,
                "vaultLevitateTotal": 3,
                "vaultBoostPlayed": 3,
                "endgameRobot3": "Parking",
                "autoPoints": 43,
                "adjustPoints": 0,
                "teleopScaleOwnershipSec": 136,
                "totalPoints": 435,
                "vaultForcePlayed": 3,
                "endgameRobot1": "Levitate",
                "endgamePoints": 65,
                "autoRunPoints": 15,
                "vaultForceTotal": 3,
                "autoSwitchAtZero": true,
                "autoOwnershipPoints": 28,
                "foulPoints": 0,
                "rp": 3,
                "teleopOwnershipPoints": 282,
                "teleopSwitchForceSec": 10,
                "tba_gameData": "RLR",
                "teleopScaleBoostSec": 0,
                "autoRobot3": "AutoRun",
                "vaultPoints": 45,
                "vaultLevitatePlayed": 3,
                "autoQuestRankingPoint": true,
                "teleopPoints": 392
            }
        },
        "name": "score_breakdown"
    },
    {
        "size": 1520116742,
        "name": "predicted_time"
    },
    {
        "size": "red",
        "name": "winning_alliance"
    },
    {
        "size": "qm",
        "name": "comp_level"
    },
    {
        "size": {
            "blue": {
                "team_keys": [
                    "frc4681",
                    "frc3812",
                    "frc2147"
                ],
                "surrogate_team_keys": [],
                "dq_team_keys": [],
                "score": 25
            },
            "red": {
                "team_keys": [
                    "frc1318",
                    "frc2910",
                    "frc3070"
                ],
                "surrogate_team_keys": [],
                "dq_team_keys": [],
                "score": 435
            }
        },
        "name": "alliances"
    },
    {
        "size": 1520113500,
        "name": "time"
    },
    {
        "size": "2018wamou",
        "name": "event_key"
    },
    {
        "size": [
            {
                "key": "8SF0DsG50OA",
                "type": "youtube"
            }
        ],
        "name": "videos"
    },
    {
        "size": "2018wamou_qm16",
        "name": "key"
    },
    {
        "size": 1,
        "name": "set_number"
    },
    {
        "size": 1520116634,
        "name": "actual_time"
    },
    {
        "size": 16,
        "name": "match_number"
    }
]
