{
    "set_number": 1,
    "time": 1520105700,
    "actual_time": 1520110907,
    "comp_level": "qm",
    "post_result_time": 1520111084,
    "videos": [
        {
            "type": "youtube",
            "key": "awqocEO5B0o"
        }
    ],
    "score_breakdown": {
        "red": {
            "teleopSwitchForceSec": 0,
            "autoRobot1": "AutoRun",
            "teleopScaleOwnershipSec": 125,
            "vaultForcePlayed": 0,
            "vaultLevitateTotal": 3,
            "tba_gameData": "RRR",
            "endgameRobot3": "Climbing",
            "teleopScaleForceSec": 0,
            "endgamePoints": 65,
            "autoRobot2": "AutoRun",
            "vaultLevitatePlayed": 3,
            "autoOwnershipPoints": 0,
            "foulCount": 0,
            "vaultPoints": 20,
            "teleopScaleBoostSec": 0,
            "totalPoints": 368,
            "vaultBoostPlayed": 1,
            "adjustPoints": 0,
            "autoQuestRankingPoint": false,
            "endgameRobot1": "Parking",
            "autoRunPoints": 15,
            "autoPoints": 15,
            "autoScaleOwnershipSec": 0,
            "foulPoints": 0,
            "teleopPoints": 353,
            "faceTheBossRankingPoint": false,
            "teleopSwitchOwnershipSec": 133,
            "techFoulCount": 0,
            "teleopOwnershipPoints": 268,
            "teleopSwitchBoostSec": 10,
            "rp": 2,
            "autoSwitchOwnershipSec": 0,
            "autoRobot3": "AutoRun",
            "vaultBoostTotal": 1,
            "endgameRobot2": "Levitate",
            "autoSwitchAtZero": false,
            "vaultForceTotal": 0
        },
        "blue": {
            "teleopSwitchForceSec": 0,
            "autoRobot1": "AutoRun",
            "teleopScaleOwnershipSec": 0,
            "vaultForcePlayed": 0,
            "vaultLevitateTotal": 0,
            "tba_gameData": "RRR",
            "endgameRobot3": "None",
            "teleopScaleForceSec": 0,
            "endgamePoints": 5,
            "autoRobot2": "AutoRun",
            "vaultLevitatePlayed": 0,
            "autoOwnershipPoints": 0,
            "foulCount": 0,
            "vaultPoints": 0,
            "teleopScaleBoostSec": 0,
            "totalPoints": 20,
            "vaultBoostPlayed": 0,
            "adjustPoints": 0,
            "autoQuestRankingPoint": false,
            "endgameRobot1": "Parking",
            "autoRunPoints": 15,
            "autoPoints": 15,
            "autoScaleOwnershipSec": 0,
            "foulPoints": 0,
            "teleopPoints": 5,
            "faceTheBossRankingPoint": false,
            "teleopSwitchOwnershipSec": 0,
            "techFoulCount": 0,
            "teleopOwnershipPoints": 0,
            "teleopSwitchBoostSec": 0,
            "rp": 0,
            "autoSwitchOwnershipSec": 0,
            "autoRobot3": "AutoRun",
            "vaultBoostTotal": 0,
            "endgameRobot2": "None",
            "autoSwitchAtZero": false,
            "vaultForceTotal": 0
        }
    },
    "key": "2018wamou_qm6",
    "predicted_time": 1520110922,
    "match_number": 6,
    "winning_alliance": "red",
    "alliances": {
        "red": {
            "team_keys": [
                "frc488",
                "frc3812",
                "frc2910"
            ],
            "dq_team_keys": [],
            "surrogate_team_keys": [],
            "score": 368
        },
        "blue": {
            "team_keys": [
                "frc4512",
                "frc7118",
                "frc4060"
            ],
            "dq_team_keys": [],
            "surrogate_team_keys": [],
            "score": 20
        }
    },
    "event_key": "2018wamou"
}